abmarl/__init__.py
abmarl/debug.py
abmarl/make_runnable.py
abmarl/stage.py
abmarl/train.py
abmarl/algs/__init__.py
abmarl/algs/monte_carlo.py
abmarl/examples/__init__.py
abmarl/examples/sim/__init__.py
abmarl/examples/sim/comms_blocking.py
abmarl/examples/sim/maze_navigation.py
abmarl/examples/sim/multi_agent_grid_sim.py
abmarl/examples/sim/multi_agent_sim.py
abmarl/examples/sim/multi_corridor.py
abmarl/examples/sim/multi_maze_navigation.py
abmarl/examples/sim/pacman.py
abmarl/examples/sim/reach_the_target.py
abmarl/examples/sim/team_battle_example.py
abmarl/examples/sim/traffic_corridor.py
abmarl/external/__init__.py
abmarl/external/gym_env_wrapper.py
abmarl/external/open_spiel_env_wrapper.py
abmarl/external/rllib_multiagentenv_wrapper.py
abmarl/managers/__init__.py
abmarl/managers/all_step_manager.py
abmarl/managers/dynamic_order_manager.py
abmarl/managers/simulation_manager.py
abmarl/managers/turn_based_manager.py
abmarl/policies/__init__.py
abmarl/policies/policy.py
abmarl/policies/q_table_policy.py
abmarl/scripts/__init__.py
abmarl/scripts/analyze_script.py
abmarl/scripts/debug_script.py
abmarl/scripts/make_runnable_script.py
abmarl/scripts/scripts.py
abmarl/scripts/train_script.py
abmarl/scripts/visualize_script.py
abmarl/sim/__init__.py
abmarl/sim/agent_based_simulation.py
abmarl/sim/gridworld/__init__.py
abmarl/sim/gridworld/actor.py
abmarl/sim/gridworld/agent.py
abmarl/sim/gridworld/base.py
abmarl/sim/gridworld/done.py
abmarl/sim/gridworld/grid.py
abmarl/sim/gridworld/observer.py
abmarl/sim/gridworld/registry.py
abmarl/sim/gridworld/smart.py
abmarl/sim/gridworld/state.py
abmarl/sim/gridworld/utils.py
abmarl/sim/gridworld/wrapper.py
abmarl/sim/wrappers/__init__.py
abmarl/sim/wrappers/communication_wrapper.py
abmarl/sim/wrappers/flatten_wrapper.py
abmarl/sim/wrappers/ravel_discrete_wrapper.py
abmarl/sim/wrappers/sar_wrapper.py
abmarl/sim/wrappers/super_agent_wrapper.py
abmarl/sim/wrappers/wrapper.py
abmarl/tools/__init__.py
abmarl/tools/gym_utils.py
abmarl-0.2.8.dist-info/LICENSE
abmarl-0.2.8.dist-info/METADATA
abmarl-0.2.8.dist-info/NOTICE
abmarl-0.2.8.dist-info/WHEEL
abmarl-0.2.8.dist-info/entry_points.txt
abmarl-0.2.8.dist-info/top_level.txt
abmarl-0.2.8.dist-info/RECORD
