Metadata-Version: 2.1
Name: abmarl
Version: 0.2.8
Summary: Agent Based Simulation and MultiAgent Reinforcement Learning
Home-page: https://github.com/llnl/abmarl
Author: Ephraim Rusu
Author-email: rusu1@llnl.gov
License: BSD 3
Project-URL: Featured Usage, https://abmarl.readthedocs.io/en/latest/featured_usage.html
Project-URL: Documentation, https://abmarl.readthedocs.io/en/latest/index.html
Classifier: Development Status :: 4 - Beta
Classifier: Intended Audience :: Science/Research
Classifier: License :: OSI Approved :: BSD License
Classifier: Natural Language :: English
Classifier: Operating System :: Unix
Classifier: Programming Language :: Python :: 3.7
Classifier: Programming Language :: Python :: 3.8
Classifier: Programming Language :: Python :: 3.9
Classifier: Programming Language :: Python :: 3.10
Classifier: Topic :: Scientific/Engineering :: Artificial Intelligence
Requires-Python: >=3.7, <3.11
License-File: LICENSE
License-File: NOTICE
Requires-Dist: importlib-metadata <5.0
Requires-Dist: numpy <1.24
Requires-Dist: gym
Requires-Dist: matplotlib
Requires-Dist: seaborn
Provides-Extra: open-spiel
Requires-Dist: open-spiel ; extra == 'open-spiel'
Provides-Extra: rllib
Requires-Dist: tensorflow ; extra == 'rllib'
Requires-Dist: ray[rllib] ==2.0.0 ; extra == 'rllib'
